numq/__init__.py
numq/_base_function.py
numq/_register.py
numq/_version.py
numq/bloch_sphere.py
numq/cupy_impl.py
numq/numpy_gates.py
numq/numpy_impl.py
numq/tf_impl.py
numq/cupy_impl_cuda_source/__init__.py
numq/cupy_impl_cuda_source/wrapper.py
numq/tests/__init__.py
numq/tests/test_cupy.py
numq/tests/test_numpy.py
numq/tests/test_tf.py
numq-1.0.1a7.dist-info/LICENSE
numq-1.0.1a7.dist-info/METADATA
numq-1.0.1a7.dist-info/WHEEL
numq-1.0.1a7.dist-info/top_level.txt
numq-1.0.1a7.dist-info/RECORD
