Metadata-Version: 2.1
Name: numq
Version: 1.0.1a7
Summary: Numerical tools for quantum experiments.
Home-page: https://github.com/we-taper/numq
Author: Taper
Author-email: h.chen.17@ucl.ac.uk
License: GNU GPLv3
Project-URL: Source Code, https://github.com/we-taper/numq
Platform: UNKNOWN
Classifier: License :: OSI Approved :: GNU General Public License v3 (GPLv3)
Classifier: Intended Audience :: Developers
Classifier: Intended Audience :: Science/Research
Classifier: Operating System :: POSIX :: Linux
Classifier: Programming Language :: Python :: 3.6
Classifier: Programming Language :: Python :: 3.7
Classifier: Programming Language :: Python :: 3.8
Classifier: Topic :: Scientific/Engineering
Requires-Python: >=3.6, <4
Requires-Dist: numpy
Requires-Dist: numba
